discounts_pkg/__init__.py
discounts_pkg/discounts.py
discounts_pkg_YOUR_USERNAME_HERE-0.0.1.dist-info/LICENSE
discounts_pkg_YOUR_USERNAME_HERE-0.0.1.dist-info/METADATA
discounts_pkg_YOUR_USERNAME_HERE-0.0.1.dist-info/WHEEL
discounts_pkg_YOUR_USERNAME_HERE-0.0.1.dist-info/top_level.txt
discounts_pkg_YOUR_USERNAME_HERE-0.0.1.dist-info/RECORD
