Metadata-Version: 2.1
Name: discounts-pkg-YOUR-USERNAME-HERE
Version: 0.0.1
Summary: A small example package to get discounts based on new user or total purchase
Home-page: https://github.com/pypa/sampleproject
Author: nandhini
Author-email: author@example.com
License: UNKNOWN
Platform: UNKNOWN
Classifier: Programming Language :: Python :: 3
Classifier: License :: OSI Approved :: MIT License
Classifier: Operating System :: OS Independent
Requires-Python: >=3.6
License-File: LICENSE
